infinisdk/__init__.py
infinisdk/entry_point.py
infinisdk/core/__init__.py
infinisdk/core/bindings.py
infinisdk/core/config.py
infinisdk/core/events.py
infinisdk/core/exceptions.py
infinisdk/core/extensions.py
infinisdk/core/field.py
infinisdk/core/field_filter.py
infinisdk/core/field_sorting.py
infinisdk/core/object_query.py
infinisdk/core/proxies.py
infinisdk/core/q.py
infinisdk/core/system_component.py
infinisdk/core/system_object.py
infinisdk/core/system_object_utils.py
infinisdk/core/translators_and_types.py
infinisdk/core/type_binder.py
infinisdk/core/type_binder_container.py
infinisdk/core/api/__init__.py
infinisdk/core/api/api.py
infinisdk/core/api/api_target.py
infinisdk/core/api/special_values.py
infinisdk/core/utils/__init__.py
infinisdk/core/utils/environment.py
infinisdk/core/utils/python.py
infinisdk/core/utils/query_utils.py
infinisdk/core/utils/replication.py
infinisdk/core/utils/resolvers.py
infinisdk/infinibox/__init__.py
infinisdk/infinibox/active_directory.py
infinisdk/infinibox/capacities.py
infinisdk/infinibox/certificates.py
infinisdk/infinibox/compatibility.py
infinisdk/infinibox/component_query.py
infinisdk/infinibox/components.py
infinisdk/infinibox/cons_group.py
infinisdk/infinibox/dataset.py
infinisdk/infinibox/events.py
infinisdk/infinibox/export.py
infinisdk/infinibox/fc_soft_target.py
infinisdk/infinibox/fc_switch.py
infinisdk/infinibox/filesystem.py
infinisdk/infinibox/host.py
infinisdk/infinibox/host_cluster.py
infinisdk/infinibox/infinibox.py
infinisdk/infinibox/initiator.py
infinisdk/infinibox/kms.py
infinisdk/infinibox/ldap_config.py
infinisdk/infinibox/link.py
infinisdk/infinibox/lun.py
infinisdk/infinibox/metadata.py
infinisdk/infinibox/metadata_holder.py
infinisdk/infinibox/network_interface.py
infinisdk/infinibox/network_space.py
infinisdk/infinibox/nfs_user.py
infinisdk/infinibox/nlm_lock.py
infinisdk/infinibox/notification_rule.py
infinisdk/infinibox/notification_target.py
infinisdk/infinibox/plugin.py
infinisdk-258.0.2.dist-info/licenses/LICENSE
infinisdk-258.0.2.dist-info/METADATA
infinisdk-258.0.2.dist-info/WHEEL
infinisdk-258.0.2.dist-info/entry_points.txt
infinisdk-258.0.2.dist-info/pbr.json
infinisdk-258.0.2.dist-info/top_level.txt
infinisdk-258.0.2.dist-info/RECORD
