Metadata-Version: 2.4
Name: infinisdk
Version: 258.0.2
Summary: Infinidat API SDK
Home-page: https://infinisdk.readthedocs.io/en/latest/
Author: Infinidat
Author-email: info@infinidat.com
License: BSD
Classifier: Programming Language :: Python :: 3.6
Classifier: Programming Language :: Python :: 3.7
Classifier: Programming Language :: Python :: 3.8
Classifier: Programming Language :: Python :: 3.9
Classifier: Programming Language :: Python :: 3.10
Requires-Python: >=3.6
License-File: LICENSE
Requires-Dist: api_object_schema>=1.5.1
Requires-Dist: arrow>=0.6.0
Requires-Dist: capacity>=1.3.8
Requires-Dist: colorama
Requires-Dist: confetti>=2.1.0
Requires-Dist: click>=8.0.4
Requires-Dist: flux
Requires-Dist: gossip>=2.3.1
Requires-Dist: infi.dtypes.wwn>=0.0.2
Requires-Dist: infi.dtypes.iqn>=0.3.0
Requires-Dist: infi.dtypes.nqn
Requires-Dist: logbook>=0.11.0
Requires-Dist: munch
Requires-Dist: mitba
Requires-Dist: pact>=1.0.0
Requires-Dist: python-dateutil
Requires-Dist: requests>=2.4.0
Requires-Dist: sentinels
Requires-Dist: storage_interfaces
Requires-Dist: URLObject
Requires-Dist: vintage>=0.4.0
Provides-Extra: doc
Requires-Dist: alabaster; extra == "doc"
Requires-Dist: sphinx; extra == "doc"
Provides-Extra: testing
Requires-Dist: click~=8.0.4; extra == "testing"
Requires-Dist: pytest>=4.6.0; extra == "testing"
Requires-Dist: astroid>=2.0; extra == "testing"
Requires-Dist: pylint>=2.0; extra == "testing"
Requires-Dist: isort~=5.0.9; extra == "testing"
Requires-Dist: black~=21.8b0; extra == "testing"
Requires-Dist: pyforge; extra == "testing"
Requires-Dist: waiting; extra == "testing"
Requires-Dist: infinisim~=258.0.0; extra == "testing"
Dynamic: author
Dynamic: author-email
Dynamic: description
Dynamic: license
Dynamic: license-file
Dynamic: provides-extra
Dynamic: requires-dist
Dynamic: requires-python
